{
    "configurations": [
        {
            "name": "Linux",
            "intelliSenseMode": "linux-gcc-x64",
            "cStandard": "c11",
            "cppStandard": "c++17",
            "includePath": [
                "${workspaceFolder}/src",
                "~/SFML-2.5.1/include",
                "/usr/local/include/**",
                "/usr/include/**",
                "${workspaceFolder}/include/**"
            ],
            "forcedInclude": [
                "${workspaceFolder}/src/pch.hpp"
            ]
        },
        {
            "name": "Mac",
            "intelliSenseMode": "macos-clang-x64",
            "compilerPath": "/usr/bin/clang",
            "cStandard": "c11",
            "cppStandard": "c++17",
            "macFrameworkPath": [
                "/Library/Frameworks",
                "/System/Library/Frameworks"
            ],
            "includePath": [
                "${workspaceFolder}/src",
                "/usr/local/include/**",
                "${workspaceFolder}/include"
            ],
            "forcedInclude": [
                "${workspaceFolder}/src/pch.h"
            ]
        },
        {
            "name": "Win32",
            "intelliSenseMode": "windows-gcc-x86",
            "cStandard": "c11",
            "cppStandard": "c++17",
            "compilerPath": "C:/mingw32/bin/gcc.exe",
            "includePath": [
                "${workspaceFolder}/src",
                "C:/SFML-2.5.1/include"
            ],
            "forcedInclude": [
                "${workspaceFolder}/src/pch.hpp"
            ]
        }
    ],
    "version": 4
}